{
  "date": "2015-11-14",
  "games": [
    {
      "away_team": "Montana State",
      "edge_home_points": null,
      "game_id": "2015_11_14_montana_state_hawai_i",
      "home_team": "Hawai'i",
      "market_spread_home": null,
      "model_mu_home": 11.381054,
      "neutral_site": null,
      "pick_cover_prob": null,
      "pick_ev_per_1": null,
      "pick_fair_odds": null,
      "pick_prob_edge": null,
      "pick_side": "AWAY",
      "pick_spread_odds": -110,
      "pred_home_win_prob": 0.923757,
      "pred_sigma": 19.548927,
      "start_time": "2015-11-14T05:30:00.000Z"
    },
    {
      "away_team": "Colorado State",
      "edge_home_points": 2.4448089999999993,
      "game_id": "2015_11_14_colorado_state_northern_iowa",
      "home_team": "Northern Iowa",
      "market_spread_home": -8.0,
      "model_mu_home": 10.444809,
      "neutral_site": null,
      "pick_cover_prob": 0.551688508152074,
      "pick_ev_per_1": 0.05322351556305038,
      "pick_fair_odds": -123.05919392742561,
      "pick_prob_edge": 0.027878984342550206,
      "pick_side": "HOME",
      "pick_spread_odds": -110,
      "pred_home_win_prob": 0.9171512,
      "pred_sigma": 18.81657,
      "start_time": "2015-11-14T17:00:00.000Z"
    },
    {
      "away_team": "Howard",
      "edge_home_points": null,
      "game_id": "2015_11_14_howard_massachusetts",
      "home_team": "Massachusetts",
      "market_spread_home": null,
      "model_mu_home": 10.723103,
      "neutral_site": null,
      "pick_cover_prob": null,
      "pick_ev_per_1": null,
      "pick_fair_odds": null,
      "pick_prob_edge": null,
      "pick_side": "AWAY",
      "pick_spread_odds": -110,
      "pred_home_win_prob": 0.924055,
      "pred_sigma": 17.52136,
      "start_time": "2015-11-14T17:00:00.000Z"
    },
    {
      "away_team": "Radford",
      "edge_home_points": null,
      "game_id": "2015_11_14_radford_georgetown",
      "home_team": "Georgetown",
      "market_spread_home": null,
      "model_mu_home": 10.029956,
      "neutral_site": null,
      "pick_cover_prob": null,
      "pick_ev_per_1": null,
      "pick_fair_odds": null,
      "pick_prob_edge": null,
      "pick_side": "AWAY",
      "pick_spread_odds": -110,
      "pred_home_win_prob": 0.90861636,
      "pred_sigma": 15.900461,
      "start_time": "2015-11-14T17:00:00.000Z"
    },
    {
      "away_team": "VMI",
      "edge_home_points": -1.0571140000000003,
      "game_id": "2015_11_14_vmi_penn_state",
      "home_team": "Penn State",
      "market_spread_home": -13.5,
      "model_mu_home": 12.442886,
      "neutral_site": null,
      "pick_cover_prob": 0.5202639855144966,
      "pick_ev_per_1": -0.006768754926870124,
      "pick_fair_odds": -108.44797342814833,
      "pick_prob_edge": -0.0035455382950272396,
      "pick_side": "AWAY",
      "pick_spread_odds": -110,
      "pred_home_win_prob": 0.923757,
      "pred_sigma": 20.802721,
      "start_time": "2015-11-14T18:00:00.000Z"
    },
    {
      "away_team": "Florida Gulf Coast",
      "edge_home_points": null,
      "game_id": "2015_11_14_florida_gulf_coast_ohio",
      "home_team": "Ohio",
      "market_spread_home": null,
      "model_mu_home": 12.114416,
      "neutral_site": null,
      "pick_cover_prob": null,
      "pick_ev_per_1": null,
      "pick_fair_odds": null,
      "pick_prob_edge": null,
      "pick_side": "AWAY",
      "pick_spread_odds": -110,
      "pred_home_win_prob": 0.923757,
      "pred_sigma": 20.968212,
      "start_time": "2015-11-14T19:00:00.000Z"
    },
    {
      "away_team": "Jacksonville",
      "edge_home_points": null,
      "game_id": "2015_11_14_jacksonville_app_state",
      "home_team": "App State",
      "market_spread_home": null,
      "model_mu_home": 10.932986,
      "neutral_site": null,
      "pick_cover_prob": null,
      "pick_ev_per_1": null,
      "pick_fair_odds": null,
      "pick_prob_edge": null,
      "pick_side": "AWAY",
      "pick_spread_odds": -110,
      "pred_home_win_prob": 0.923757,
      "pred_sigma": 17.908213,
      "start_time": "2015-11-14T19:00:00.000Z"
    },
    {
      "away_team": "New Orleans",
      "edge_home_points": null,
      "game_id": "2015_11_14_new_orleans_bowling_green",
      "home_team": "Bowling Green",
      "market_spread_home": null,
      "model_mu_home": 10.404871,
      "neutral_site": null,
      "pick_cover_prob": null,
      "pick_ev_per_1": null,
      "pick_fair_odds": null,
      "pick_prob_edge": null,
      "pick_side": "AWAY",
      "pick_spread_odds": -110,
      "pred_home_win_prob": 0.923757,
      "pred_sigma": 16.37812,
      "start_time": "2015-11-14T19:00:00.000Z"
    },
    {
      "away_team": "St. Francis Brooklyn",
      "edge_home_points": null,
      "game_id": "2015_11_14_st_francis_brooklyn_boston_college",
      "home_team": "Boston College",
      "market_spread_home": null,
      "model_mu_home": 9.530643,
      "neutral_site": null,
      "pick_cover_prob": null,
      "pick_ev_per_1": null,
      "pick_fair_odds": null,
      "pick_prob_edge": null,
      "pick_side": "AWAY",
      "pick_spread_odds": -110,
      "pred_home_win_prob": 0.8898348,
      "pred_sigma": 15.646701,
      "start_time": "2015-11-14T19:00:00.000Z"
    },
    {
      "away_team": "Grambling",
      "edge_home_points": null,
      "game_id": "2015_11_14_grambling_mid_atlantic_christian",
      "home_team": "Mid-Atlantic Christian",
      "market_spread_home": null,
      "model_mu_home": 17.685326,
      "neutral_site": null,
      "pick_cover_prob": null,
      "pick_ev_per_1": null,
      "pick_fair_odds": null,
      "pick_prob_edge": null,
      "pick_side": "AWAY",
      "pick_spread_odds": -110,
      "pred_home_win_prob": 0.9926923,
      "pred_sigma": 9.122035,
      "start_time": "2015-11-14T19:00:00.000Z"
    },
    {
      "away_team": "WVU Tech",
      "edge_home_points": null,
      "game_id": "2015_11_14_wvu_tech_toledo",
      "home_team": "Toledo",
      "market_spread_home": null,
      "model_mu_home": 12.867211,
      "neutral_site": null,
      "pick_cover_prob": null,
      "pick_ev_per_1": null,
      "pick_fair_odds": null,
      "pick_prob_edge": null,
      "pick_side": "AWAY",
      "pick_spread_odds": -110,
      "pred_home_win_prob": 0.923757,
      "pred_sigma": 22.656492,
      "start_time": "2015-11-14T19:30:00.000Z"
    },
    {
      "away_team": "Towson",
      "edge_home_points": 1.3775370000000002,
      "game_id": "2015_11_14_towson_la_salle",
      "home_team": "La Salle",
      "market_spread_home": -10.0,
      "model_mu_home": 11.377537,
      "neutral_site": null,
      "pick_cover_prob": 0.5296126339832685,
      "pick_ev_per_1": 0.01107866487714898,
      "pick_fair_odds": -112.59074376679376,
      "pick_prob_edge": 0.0058031101737446855,
      "pick_side": "HOME",
      "pick_spread_odds": -110,
      "pred_home_win_prob": 0.91341573,
      "pred_sigma": 18.54116,
      "start_time": "2015-11-14T20:00:00.000Z"
    },
    {
      "away_team": "Hampton",
      "edge_home_points": null,
      "game_id": "2015_11_14_hampton_winthrop",
      "home_team": "Winthrop",
      "market_spread_home": null,
      "model_mu_home": 10.895189,
      "neutral_site": null,
      "pick_cover_prob": null,
      "pick_ev_per_1": null,
      "pick_fair_odds": null,
      "pick_prob_edge": null,
      "pick_side": "AWAY",
      "pick_spread_odds": -110,
      "pred_home_win_prob": 0.92212176,
      "pred_sigma": 19.124783,
      "start_time": "2015-11-14T21:00:00.000Z"
    },
    {
      "away_team": "Central Baptist College",
      "edge_home_points": null,
      "game_id": "2015_11_14_central_baptist_college_little_rock",
      "home_team": "Little Rock",
      "market_spread_home": null,
      "model_mu_home": 10.59821,
      "neutral_site": null,
      "pick_cover_prob": null,
      "pick_ev_per_1": null,
      "pick_fair_odds": null,
      "pick_prob_edge": null,
      "pick_side": "AWAY",
      "pick_spread_odds": -110,
      "pred_home_win_prob": 0.923007,
      "pred_sigma": 19.166782,
      "start_time": "2015-11-14T21:00:00.000Z"
    },
    {
      "away_team": "Averett",
      "edge_home_points": null,
      "game_id": "2015_11_14_averett_east_tennessee_state",
      "home_team": "East Tennessee State",
      "market_spread_home": null,
      "model_mu_home": 10.806347,
      "neutral_site": null,
      "pick_cover_prob": null,
      "pick_ev_per_1": null,
      "pick_fair_odds": null,
      "pick_prob_edge": null,
      "pick_side": "AWAY",
      "pick_spread_odds": -110,
      "pred_home_win_prob": 0.92442644,
      "pred_sigma": 19.303558,
      "start_time": "2015-11-14T21:00:00.000Z"
    },
    {
      "away_team": "South Dakota",
      "edge_home_points": -3.739051,
      "game_id": "2015_11_14_south_dakota_northern_illinois",
      "home_team": "Northern Illinois",
      "market_spread_home": -9.0,
      "model_mu_home": 5.260949,
      "neutral_site": null,
      "pick_cover_prob": 0.604649672662852,
      "pick_ev_per_1": 0.15433119326544464,
      "pick_fair_odds": -152.9402231017295,
      "pick_prob_edge": 0.08084014885332813,
      "pick_side": "AWAY",
      "pick_spread_odds": -110,
      "pred_home_win_prob": 0.8460637,
      "pred_sigma": 14.088314,
      "start_time": "2015-11-14T21:30:00.000Z"
    },
    {
      "away_team": "Greensboro College",
      "edge_home_points": null,
      "game_id": "2015_11_14_greensboro_college_unc_greensboro",
      "home_team": "UNC Greensboro",
      "market_spread_home": null,
      "model_mu_home": 11.284067,
      "neutral_site": null,
      "pick_cover_prob": null,
      "pick_ev_per_1": null,
      "pick_fair_odds": null,
      "pick_prob_edge": null,
      "pick_side": "AWAY",
      "pick_spread_odds": -110,
      "pred_home_win_prob": 0.8998619,
      "pred_sigma": 20.522749,
      "start_time": "2015-11-14T22:00:00.000Z"
    },
    {
      "away_team": "Central Arkansas",
      "edge_home_points": null,
      "game_id": "2015_11_14_central_arkansas_tulsa",
      "home_team": "Tulsa",
      "market_spread_home": null,
      "model_mu_home": 11.429073,
      "neutral_site": null,
      "pick_cover_prob": null,
      "pick_ev_per_1": null,
      "pick_fair_odds": null,
      "pick_prob_edge": null,
      "pick_side": "AWAY",
      "pick_spread_odds": -110,
      "pred_home_win_prob": 0.923757,
      "pred_sigma": 18.855255,
      "start_time": "2015-11-14T22:00:00.000Z"
    },
    {
      "away_team": "Harvard",
      "edge_home_points": -8.186356,
      "game_id": "2015_11_14_harvard_providence",
      "home_team": "Providence",
      "market_spread_home": -10.0,
      "model_mu_home": 1.813644,
      "neutral_site": null,
      "pick_cover_prob": 0.7190306081570204,
      "pick_ev_per_1": 0.37269479739067524,
      "pick_fair_odds": -255.91065398285525,
      "pick_prob_edge": 0.19522108434749652,
      "pick_side": "AWAY",
      "pick_spread_odds": -110,
      "pred_home_win_prob": 0.2912638,
      "pred_sigma": 14.115279,
      "start_time": "2015-11-15T00:00:00.000Z"
    },
    {
      "away_team": "Youngstown State",
      "edge_home_points": 1.5101794999999996,
      "game_id": "2015_11_14_youngstown_state_kent_state",
      "home_team": "Kent State",
      "market_spread_home": -10.0,
      "model_mu_home": 11.5101795,
      "neutral_site": null,
      "pick_cover_prob": 0.532628514281009,
      "pick_ev_per_1": 0.016836254536471695,
      "pick_fair_odds": -113.96256095119462,
      "pick_prob_edge": 0.008818990471485155,
      "pick_side": "HOME",
      "pick_spread_odds": -110,
      "pred_home_win_prob": 0.923757,
      "pred_sigma": 18.44405,
      "start_time": "2015-11-15T00:00:00.000Z"
    },
    {
      "away_team": "Montana State",
      "edge_home_points": null,
      "game_id": "2015_11_14_montana_state_hawai_i_hilo",
      "home_team": "Hawai'i Hilo",
      "market_spread_home": null,
      "model_mu_home": 11.48512,
      "neutral_site": null,
      "pick_cover_prob": null,
      "pick_ev_per_1": null,
      "pick_fair_odds": null,
      "pick_prob_edge": null,
      "pick_side": "AWAY",
      "pick_spread_odds": -110,
      "pred_home_win_prob": 0.22574253,
      "pred_sigma": 12.667895,
      "start_time": "2015-11-15T00:00:00.000Z"
    },
    {
      "away_team": "BYU-Hawaii",
      "edge_home_points": null,
      "game_id": "2015_11_14_byu_hawaii_long_beach_state",
      "home_team": "Long Beach State",
      "market_spread_home": null,
      "model_mu_home": 11.377015,
      "neutral_site": null,
      "pick_cover_prob": null,
      "pick_ev_per_1": null,
      "pick_fair_odds": null,
      "pick_prob_edge": null,
      "pick_side": "AWAY",
      "pick_spread_odds": -110,
      "pred_home_win_prob": 0.92881775,
      "pred_sigma": 22.447449,
      "start_time": "2015-11-15T00:00:00.000Z"
    },
    {
      "away_team": "Norfolk State",
      "edge_home_points": null,
      "game_id": "2015_11_14_norfolk_state_south_carolina",
      "home_team": "South Carolina",
      "market_spread_home": null,
      "model_mu_home": 9.552912,
      "neutral_site": null,
      "pick_cover_prob": null,
      "pick_ev_per_1": null,
      "pick_fair_odds": null,
      "pick_prob_edge": null,
      "pick_side": "AWAY",
      "pick_spread_odds": -110,
      "pred_home_win_prob": 0.8976397,
      "pred_sigma": 12.360941,
      "start_time": "2015-11-15T00:00:00.000Z"
    },
    {
      "away_team": "Jessup University",
      "edge_home_points": null,
      "game_id": "2015_11_14_jessup_university_uc_riverside",
      "home_team": "UC Riverside",
      "market_spread_home": null,
      "model_mu_home": 11.815933,
      "neutral_site": null,
      "pick_cover_prob": null,
      "pick_ev_per_1": null,
      "pick_fair_odds": null,
      "pick_prob_edge": null,
      "pick_side": "AWAY",
      "pick_spread_odds": -110,
      "pred_home_win_prob": 0.923757,
      "pred_sigma": 21.44416,
      "start_time": "2015-11-15T00:00:00.000Z"
    },
    {
      "away_team": "Wright State",
      "edge_home_points": 5.7452385,
      "game_id": "2015_11_14_wright_state_cal_state_northridge",
      "home_team": "Cal State Northridge",
      "market_spread_home": 7.5,
      "model_mu_home": -1.7547615,
      "neutral_site": null,
      "pick_cover_prob": 0.6932979604866585,
      "pick_ev_per_1": 0.32356883365634803,
      "pick_fair_odds": -226.0493479556728,
      "pick_prob_edge": 0.16948843667713465,
      "pick_side": "HOME",
      "pick_spread_odds": -110,
      "pred_home_win_prob": 0.12757733,
      "pred_sigma": 11.371748,
      "start_time": "2015-11-15T00:00:00.000Z"
    },
    {
      "away_team": "Alabama State",
      "edge_home_points": null,
      "game_id": "2015_11_14_alabama_state_virginia_tech",
      "home_team": "Virginia Tech",
      "market_spread_home": null,
      "model_mu_home": 8.31702,
      "neutral_site": null,
      "pick_cover_prob": null,
      "pick_ev_per_1": null,
      "pick_fair_odds": null,
      "pick_prob_edge": null,
      "pick_side": "AWAY",
      "pick_spread_odds": -110,
      "pred_home_win_prob": 0.8372613,
      "pred_sigma": 11.163102,
      "start_time": "2015-11-15T00:00:00.000Z"
    },
    {
      "away_team": "Clarks Summit",
      "edge_home_points": null,
      "game_id": "2015_11_14_clarks_summit_liberty",
      "home_team": "Liberty",
      "market_spread_home": null,
      "model_mu_home": 7.9189043,
      "neutral_site": null,
      "pick_cover_prob": null,
      "pick_ev_per_1": null,
      "pick_fair_odds": null,
      "pick_prob_edge": null,
      "pick_side": "AWAY",
      "pick_spread_odds": -110,
      "pred_home_win_prob": 0.9157366,
      "pred_sigma": 20.00135,
      "start_time": "2015-11-15T00:00:00.000Z"
    },
    {
      "away_team": "Merchant Marine Academy",
      "edge_home_points": null,
      "game_id": "2015_11_14_merchant_marine_academy_stony_brook",
      "home_team": "Stony Brook",
      "market_spread_home": null,
      "model_mu_home": 12.404771,
      "neutral_site": null,
      "pick_cover_prob": null,
      "pick_ev_per_1": null,
      "pick_fair_odds": null,
      "pick_prob_edge": null,
      "pick_side": "AWAY",
      "pick_spread_odds": -110,
      "pred_home_win_prob": 0.923757,
      "pred_sigma": 21.820929,
      "start_time": "2015-11-15T00:00:00.000Z"
    },
    {
      "away_team": "UCF",
      "edge_home_points": -3.254671,
      "game_id": "2015_11_14_ucf_davidson",
      "home_team": "Davidson",
      "market_spread_home": -15.5,
      "model_mu_home": 12.245329,
      "neutral_site": null,
      "pick_cover_prob": 0.5582012368510292,
      "pick_ev_per_1": 0.0656569067156011,
      "pick_fair_odds": -126.3473969171816,
      "pick_prob_edge": 0.034391713041505345,
      "pick_side": "AWAY",
      "pick_spread_odds": -110,
      "pred_home_win_prob": 0.923757,
      "pred_sigma": 22.229801,
      "start_time": "2015-11-15T00:30:00.000Z"
    },
    {
      "away_team": "Bushnell",
      "edge_home_points": null,
      "game_id": "2015_11_14_bushnell_oregon_state",
      "home_team": "Oregon State",
      "market_spread_home": null,
      "model_mu_home": 12.140156,
      "neutral_site": null,
      "pick_cover_prob": null,
      "pick_ev_per_1": null,
      "pick_fair_odds": null,
      "pick_prob_edge": null,
      "pick_side": "AWAY",
      "pick_spread_odds": -110,
      "pred_home_win_prob": 0.923757,
      "pred_sigma": 22.568201,
      "start_time": "2015-11-15T00:30:00.000Z"
    },
    {
      "away_team": "The Citadel",
      "edge_home_points": -16.849922,
      "game_id": "2015_11_14_the_citadel_butler",
      "home_team": "Butler",
      "market_spread_home": -27.5,
      "model_mu_home": 10.650078,
      "neutral_site": null,
      "pick_cover_prob": 0.8602700965436483,
      "pick_ev_per_1": 0.6423338206742376,
      "pick_fair_odds": -615.6664216206061,
      "pick_prob_edge": 0.33646057273412444,
      "pick_side": "AWAY",
      "pick_spread_odds": -110,
      "pred_home_win_prob": 0.9174365,
      "pred_sigma": 15.579656,
      "start_time": "2015-11-15T00:30:00.000Z"
    },
    {
      "away_team": "Bryant",
      "edge_home_points": null,
      "game_id": "2015_11_14_bryant_duke",
      "home_team": "Duke",
      "market_spread_home": null,
      "model_mu_home": 19.127102,
      "neutral_site": null,
      "pick_cover_prob": null,
      "pick_ev_per_1": null,
      "pick_fair_odds": null,
      "pick_prob_edge": null,
      "pick_side": "AWAY",
      "pick_spread_odds": -110,
      "pred_home_win_prob": 0.998645,
      "pred_sigma": 12.35598,
      "start_time": "2015-11-15T01:00:00.000Z"
    },
    {
      "away_team": "Mississippi Valley State",
      "edge_home_points": null,
      "game_id": "2015_11_14_mississippi_valley_state_nebraska",
      "home_team": "Nebraska",
      "market_spread_home": null,
      "model_mu_home": 10.986796,
      "neutral_site": null,
      "pick_cover_prob": null,
      "pick_ev_per_1": null,
      "pick_fair_odds": null,
      "pick_prob_edge": null,
      "pick_side": "AWAY",
      "pick_spread_odds": -110,
      "pred_home_win_prob": 0.923757,
      "pred_sigma": 15.250659,
      "start_time": "2015-11-15T01:00:00.000Z"
    },
    {
      "away_team": "NJIT",
      "edge_home_points": -16.339775,
      "game_id": "2015_11_14_njit_kentucky",
      "home_team": "Kentucky",
      "market_spread_home": -25.0,
      "model_mu_home": 8.660225,
      "neutral_site": null,
      "pick_cover_prob": 0.9394851978143297,
      "pick_ev_per_1": 0.7935626503728113,
      "pick_fair_odds": -1552.4882572231174,
      "pick_prob_edge": 0.4156756740048059,
      "pick_side": "AWAY",
      "pick_spread_odds": -110,
      "pred_home_win_prob": 2.018419e-05,
      "pred_sigma": 10.538619,
      "start_time": "2015-11-15T01:00:00.000Z"
    },
    {
      "away_team": "Southern Miss",
      "edge_home_points": -2.3171809999999997,
      "game_id": "2015_11_14_southern_miss_memphis",
      "home_team": "Memphis",
      "market_spread_home": -15.0,
      "model_mu_home": 12.682819,
      "neutral_site": null,
      "pick_cover_prob": 0.5392839590773963,
      "pick_ev_per_1": 0.029542103693211197,
      "pick_fair_odds": -117.05343664558696,
      "pick_prob_edge": 0.01547443526787251,
      "pick_side": "AWAY",
      "pick_spread_odds": -110,
      "pred_home_win_prob": 0.923757,
      "pred_sigma": 23.493683,
      "start_time": "2015-11-15T01:00:00.000Z"
    },
    {
      "away_team": "Sam Houston",
      "edge_home_points": null,
      "game_id": "2015_11_14_sam_houston_smu",
      "home_team": "SMU",
      "market_spread_home": null,
      "model_mu_home": 11.688734,
      "neutral_site": null,
      "pick_cover_prob": null,
      "pick_ev_per_1": null,
      "pick_fair_odds": null,
      "pick_prob_edge": null,
      "pick_side": "AWAY",
      "pick_spread_odds": -110,
      "pred_home_win_prob": 0.923757,
      "pred_sigma": 17.630983,
      "start_time": "2015-11-15T01:00:00.000Z"
    },
    {
      "away_team": "Eureka",
      "edge_home_points": null,
      "game_id": "2015_11_14_eureka_loyola_chicago",
      "home_team": "Loyola Chicago",
      "market_spread_home": null,
      "model_mu_home": 11.933801,
      "neutral_site": null,
      "pick_cover_prob": null,
      "pick_ev_per_1": null,
      "pick_fair_odds": null,
      "pick_prob_edge": null,
      "pick_side": "AWAY",
      "pick_spread_odds": -110,
      "pred_home_win_prob": 0.9994153,
      "pred_sigma": 14.261369,
      "start_time": "2015-11-15T01:00:00.000Z"
    },
    {
      "away_team": "Campbellsville",
      "edge_home_points": null,
      "game_id": "2015_11_14_campbellsville_western_kentucky",
      "home_team": "Western Kentucky",
      "market_spread_home": null,
      "model_mu_home": 10.532092,
      "neutral_site": null,
      "pick_cover_prob": null,
      "pick_ev_per_1": null,
      "pick_fair_odds": null,
      "pick_prob_edge": null,
      "pick_side": "AWAY",
      "pick_spread_odds": -110,
      "pred_home_win_prob": 0.9219092,
      "pred_sigma": 19.646877,
      "start_time": "2015-11-15T01:00:00.000Z"
    },
    {
      "away_team": "Fordham",
      "edge_home_points": 8.164694,
      "game_id": "2015_11_14_fordham_ut_arlington",
      "home_team": "UT Arlington",
      "market_spread_home": -4.0,
      "model_mu_home": 12.164694,
      "neutral_site": null,
      "pick_cover_prob": 0.6310924074713848,
      "pick_ev_per_1": 0.20481277789991648,
      "pick_fair_odds": -171.07059335528118,
      "pick_prob_edge": 0.107282883661861,
      "pick_side": "HOME",
      "pick_spread_odds": -110,
      "pred_home_win_prob": 0.9481595,
      "pred_sigma": 24.390568,
      "start_time": "2015-11-15T01:30:00.000Z"
    },
    {
      "away_team": "Milwaukee",
      "edge_home_points": 8.5302067,
      "game_id": "2015_11_14_milwaukee_lipscomb",
      "home_team": "Lipscomb",
      "market_spread_home": 6.5,
      "model_mu_home": 2.0302067,
      "neutral_site": null,
      "pick_cover_prob": 0.7303318940748005,
      "pick_ev_per_1": 0.39426997959734633,
      "pick_fair_odds": -270.82620377709026,
      "pick_prob_edge": 0.20652237026527664,
      "pick_side": "HOME",
      "pick_spread_odds": -110,
      "pred_home_win_prob": 0.027852207,
      "pred_sigma": 13.896985,
      "start_time": "2015-11-15T01:30:00.000Z"
    },
    {
      "away_team": "Piedmont",
      "edge_home_points": null,
      "game_id": "2015_11_14_piedmont_tennessee_tech",
      "home_team": "Tennessee Tech",
      "market_spread_home": null,
      "model_mu_home": 13.022947,
      "neutral_site": null,
      "pick_cover_prob": null,
      "pick_ev_per_1": null,
      "pick_fair_odds": null,
      "pick_prob_edge": null,
      "pick_side": "AWAY",
      "pick_spread_odds": -110,
      "pred_home_win_prob": 0.923757,
      "pred_sigma": 24.835903,
      "start_time": "2015-11-15T01:50:00.000Z"
    },
    {
      "away_team": "Western Michigan",
      "edge_home_points": 3.4519959999999994,
      "game_id": "2015_11_14_western_michigan_depaul",
      "home_team": "DePaul",
      "market_spread_home": -7.0,
      "model_mu_home": 10.451996,
      "neutral_site": null,
      "pick_cover_prob": 0.5826316978639358,
      "pick_ev_per_1": 0.112296877740241,
      "pick_fair_odds": -139.59653737048646,
      "pick_prob_edge": 0.058822174054411924,
      "pick_side": "HOME",
      "pick_spread_odds": -110,
      "pred_home_win_prob": 0.923757,
      "pred_sigma": 16.54597,
      "start_time": "2015-11-15T02:00:00.000Z"
    },
    {
      "away_team": "Great Falls",
      "edge_home_points": null,
      "game_id": "2015_11_14_great_falls_utah_valley",
      "home_team": "Utah Valley",
      "market_spread_home": null,
      "model_mu_home": -9.019384,
      "neutral_site": null,
      "pick_cover_prob": null,
      "pick_ev_per_1": null,
      "pick_fair_odds": null,
      "pick_prob_edge": null,
      "pick_side": "AWAY",
      "pick_spread_odds": -110,
      "pred_home_win_prob": 0.23327923,
      "pred_sigma": 14.622137,
      "start_time": "2015-11-15T02:00:00.000Z"
    },
    {
      "away_team": "Loyola New Orleans",
      "edge_home_points": null,
      "game_id": "2015_11_14_loyola_new_orleans_utep",
      "home_team": "UTEP",
      "market_spread_home": null,
      "model_mu_home": 25.598705,
      "neutral_site": null,
      "pick_cover_prob": null,
      "pick_ev_per_1": null,
      "pick_fair_odds": null,
      "pick_prob_edge": null,
      "pick_side": "AWAY",
      "pick_spread_odds": -110,
      "pred_home_win_prob": 0.98266244,
      "pred_sigma": 14.430651,
      "start_time": "2015-11-15T02:05:00.000Z"
    },
    {
      "away_team": "Texas Southern",
      "edge_home_points": null,
      "game_id": "2015_11_14_texas_southern_creighton",
      "home_team": "Creighton",
      "market_spread_home": null,
      "model_mu_home": 14.843503,
      "neutral_site": null,
      "pick_cover_prob": null,
      "pick_ev_per_1": null,
      "pick_fair_odds": null,
      "pick_prob_edge": null,
      "pick_side": "AWAY",
      "pick_spread_odds": -110,
      "pred_home_win_prob": 0.98425597,
      "pred_sigma": 10.427688,
      "start_time": "2015-11-15T02:30:00.000Z"
    },
    {
      "away_team": "Cleveland State",
      "edge_home_points": -2.5125349,
      "game_id": "2015_11_14_cleveland_state_akron",
      "home_team": "Akron",
      "market_spread_home": -6.0,
      "model_mu_home": 3.4874651,
      "neutral_site": null,
      "pick_cover_prob": 0.5578919925174506,
      "pick_ev_per_1": 0.06506653116967842,
      "pick_fair_odds": -126.18907214420251,
      "pick_prob_edge": 0.03408246870792675,
      "pick_side": "AWAY",
      "pick_spread_odds": -110,
      "pred_home_win_prob": 0.83070624,
      "pred_sigma": 17.253246,
      "start_time": "2015-11-15T02:30:00.000Z"
    },
    {
      "away_team": "San Diego Christian",
      "edge_home_points": null,
      "game_id": "2015_11_14_san_diego_christian_cal_state_bakersfield",
      "home_team": "Cal State Bakersfield",
      "market_spread_home": null,
      "model_mu_home": 11.754505,
      "neutral_site": null,
      "pick_cover_prob": null,
      "pick_ev_per_1": null,
      "pick_fair_odds": null,
      "pick_prob_edge": null,
      "pick_side": "AWAY",
      "pick_spread_odds": -110,
      "pred_home_win_prob": 0.923757,
      "pred_sigma": 21.150372,
      "start_time": "2015-11-15T03:00:00.000Z"
    },
    {
      "away_team": "Idaho",
      "edge_home_points": 10.064495,
      "game_id": "2015_11_14_idaho_san_jos_state",
      "home_team": "San Jos\u00e9 State",
      "market_spread_home": 2.0,
      "model_mu_home": 8.064495,
      "neutral_site": null,
      "pick_cover_prob": 0.8067426545319609,
      "pick_ev_per_1": 0.5401450677428344,
      "pick_fair_odds": -417.44475615048754,
      "pick_prob_edge": 0.2829331307224371,
      "pick_side": "HOME",
      "pick_spread_odds": -110,
      "pred_home_win_prob": 0.79915375,
      "pred_sigma": 11.622419,
      "start_time": "2015-11-15T03:00:00.000Z"
    },
    {
      "away_team": "Denver",
      "edge_home_points": -2.9731565,
      "game_id": "2015_11_14_denver_santa_clara",
      "home_team": "Santa Clara",
      "market_spread_home": -6.0,
      "model_mu_home": 3.0268435,
      "neutral_site": null,
      "pick_cover_prob": 0.5820581311719384,
      "pick_ev_per_1": 0.11120188678279141,
      "pick_fair_odds": -139.26772467282836,
      "pick_prob_edge": 0.05824860736241455,
      "pick_side": "AWAY",
      "pick_spread_odds": -110,
      "pred_home_win_prob": 0.011097815,
      "pred_sigma": 14.351878,
      "start_time": "2015-11-15T04:00:00.000Z"
    }
  ],
  "generated_at": "2026-03-01T02:27:04.877111Z"
}
